COPYING
MANIFEST.in
README.rst
bootstrap.py
buildout.cfg
setup.py
bob/__init__.py
bob.db.ldhf.egg-info/PKG-INFO
bob.db.ldhf.egg-info/SOURCES.txt
bob.db.ldhf.egg-info/dependency_links.txt
bob.db.ldhf.egg-info/entry_points.txt
bob.db.ldhf.egg-info/namespace_packages.txt
bob.db.ldhf.egg-info/not-zip-safe
bob.db.ldhf.egg-info/requires.txt
bob.db.ldhf.egg-info/top_level.txt
bob/db/__init__.py
bob/db/ldhf/__init__.py
bob/db/ldhf/create.py
bob/db/ldhf/driver.py
bob/db/ldhf/models.py
bob/db/ldhf/query.py
bob/db/ldhf/test.py
bob/db/ldhf/utils.py
bob/db/ldhf/script/__init__.py
doc/conf.py
doc/guide.rst
doc/index.rst
doc/py_api.rst