Metadata-Version: 1.1
Name: bob.db.ldhf
Version: 1.0.4
Summary: Long Distance Heterogeneous Face Database (LDHF)
Home-page: https://gitlab.idiap.ch/bob/bob.db.ldhf
Author: Tiago de Freitas Pereira
Author-email: tiago.pereira@idiap.ch
License: BSD
Platform: UNKNOWN
Classifier: Development Status :: 4 - Beta
Classifier: Intended Audience :: Education
Classifier: License :: OSI Approved :: BSD License
Classifier: Natural Language :: English
Classifier: Programming Language :: Python
Classifier: Programming Language :: Python :: 3
Classifier: Topic :: Scientific/Engineering :: Artificial Intelligence
Classifier: Topic :: Database :: Front-Ends
